arcade_ashby_api/__init__.py
arcade_ashby_api/moar/Ashby.json
arcade_ashby_api/moar/openapi.json
arcade_ashby_api/tools/__init__.py
arcade_ashby_api/tools/request_body_schemas.py
arcade_ashby_api/wrapper_tools/AddCandidateTag.json
arcade_ashby_api/wrapper_tools/AddCandidateToProject.json
arcade_ashby_api/wrapper_tools/AddCompletedAssessmentToCandidate.json
arcade_ashby_api/wrapper_tools/AddHiringTeamMember.json
arcade_ashby_api/wrapper_tools/AddJobToOpening.json
arcade_ashby_api/wrapper_tools/AddLocationToJobOpening.json
arcade_ashby_api/wrapper_tools/AddUserToInterviewerPool.json
arcade_ashby_api/wrapper_tools/AnonymizeCandidateData.json
arcade_ashby_api/wrapper_tools/ArchiveDepartment.json
arcade_ashby_api/wrapper_tools/ArchiveInterviewerPool.json
arcade_ashby_api/wrapper_tools/ArchiveLocation.json
arcade_ashby_api/wrapper_tools/AshbyUserSearch.json
arcade_ashby_api/wrapper_tools/CancelAssessment.json
arcade_ashby_api/wrapper_tools/CancelInterviewSchedule.json
arcade_ashby_api/wrapper_tools/ChangeApplicationSource.json
arcade_ashby_api/wrapper_tools/CreateCandidate.json
arcade_ashby_api/wrapper_tools/CreateCandidateNote.json
arcade_ashby_api/wrapper_tools/CreateCandidateOfferVersion.json
arcade_ashby_api/wrapper_tools/CreateCandidateReferral.json
arcade_ashby_api/wrapper_tools/CreateCandidateTag.json
arcade_ashby_api/wrapper_tools/CreateCustomField.json
arcade_ashby_api/wrapper_tools/CreateDepartment.json
arcade_ashby_api/wrapper_tools/CreateInterviewSchedule.json
arcade_ashby_api/wrapper_tools/CreateInterviewerPool.json
arcade_ashby_api/wrapper_tools/CreateJobApplication.json
arcade_ashby_api/wrapper_tools/CreateJobOpening.json
arcade_ashby_api/wrapper_tools/CreateLocation.json
arcade_ashby_api/wrapper_tools/CreateNewJob.json
arcade_ashby_api/wrapper_tools/CreateOffer.json
arcade_ashby_api/wrapper_tools/CreateSurveyRequest.json
arcade_ashby_api/wrapper_tools/CreateSurveySubmission.json
arcade_ashby_api/wrapper_tools/CreateWebhookSetting.json
arcade_ashby_api-2.0.0.dist-info/METADATA
arcade_ashby_api-2.0.0.dist-info/WHEEL
arcade_ashby_api-2.0.0.dist-info/entry_points.txt
arcade_ashby_api-2.0.0.dist-info/licenses/LICENSE
arcade_ashby_api-2.0.0.dist-info/RECORD
